B90034/ProbadorTarea1.v
module Probador(CLK,ENB, MODO, D, Q, RCO, Paridad); 
//SALIDAS
output  CLK;
output  ENB; 
output  [15:0]D;
output   [1:0]MODO;
//ENTRADA
input [15:0]Q;
input RCO;
input Paridad;
//Registros
reg CLK, MODO, ENB, D; 
wire Q, RCO, Paridad; 

initial begin
    // Prueba #1, prueba ascendente
    $display("Prueba #1: Cuenta ascendente");
        CLK = 0;   
        ENB = 1;   
        MODO = 2'b11;   
        D = 0;    
        #10;    
        MODO = 2'b00;   
        #10;
        #200;
        ENB = 0;
        #40; //Tiempo de espera

      // Prueba #2, prueba descendente 
      $display("Prueba #2: Cuenta descendente");
        ENB = 1; 
        D = 15;
        MODO = 2'b11;
        #10;
        MODO = 2'b01;
        #200; 
        ENB = 0;
        #40 //Tiempo de espera

      // Prueba #3: Cuenta de tres en tres hacia arriba
      $display("Prueba #3: Cuenta de tres en tres hacia arriba");
        ENB = 1;
        D = 0; 
        MODO = 2'b11;
        #10;
        MODO = 2'b10;
        #200;
        ENB = 0;
        #40; //Tiempo de espera 

      // Prueba #4: Carga en paralelo
    $display("Prueba #4: Carga en paralelo");
    	ENB = 1;
        D = 4'bxxxx;
        #10;
        MODO = 2'b11;
        #20;
        D = 4'b1001;
        #20;
        MODO = 2'b11;
        #20;
        MODO =2'b00;
        #250; 
        ENB = 0;
        #40;//Tiempo de espera
    
      //Prueba #5, contador de 16 bits
      $display("Prueba #5:Contador de 16 bits");
        ENB = 1;
        D = 0;
        MODO = 2'b11;
        #10;
        MODO = 2'b00;
        #120;
        MODO = 2'b01;
        #120;
        MODO = 2'b10;
        #120;
        D = 30;
        MODO = 2'b11;
        #250;
        D = 0;
        MODO = 2'b11;
        #60 $finish;
    end

always 
begin
    #5 CLK=!CLK; //cambiar la unidad de retardo para el cambio del reloj, ayuda a definir el periodo de la señal 
end

endmodule

B90034/ContadorTarea1.v
module counter(
    input CLK,
    input ENB,
    input [3:0] D,
    input [1:0] MODO,
    output reg [3:0] Q,
    output reg RCO,
    output reg Paridad
);
    always @(posedge CLK) begin
        if (ENB == 1) begin
            case (MODO)
                2'b00: Q <= Q + 1; // Cuenta hacia arriba
                2'b01: Q <= Q - 1; // Cuenta hacia abajo
                2'b10: Q <= Q + 3; // Cuenta de tres en tres hacia arriba
                2'b11: Q <= D;      // Carga en paralelo
                default: Q <= Q;
            endcase
        end else begin
            Q = Q;
        end
    end

    always @(posedge CLK) begin
        if (ENB == 1) begin
            Paridad <= Paridad ^ Q[0] ^ Q[1] ^ Q[2] ^ Q[3];
        end
    end

    always @* begin
        if (Q == 4'b1111) begin
            RCO <= 1;
        end else begin
            RCO <= 0;
        end
    end
endmodule

B90034/Contador4X4.v
module Contador#(parameter N=16)(
    input CLK,
    input ENB,
    input [15:0] D,
    input [1:0] MODO,
    output wire [15:0] Q,
    output reg RCO,
    output reg Paridad
);


// Declara las señales intermedias
    wire [3:0] D_reg[N/4-1:0];
    wire [3:0] Q_reg[N/4-1:0];
    wire RCO_reg[N/4-1:0];
    wire Paridad_reg[N/4-1:0];
   
    genvar i;
   
    generate
        for (i = 0; i < N/4; i = i + 1) begin : inst_counter
            assign D_reg[i] = D[i*4 +: 4];
           
counter uut (
    .CLK(CLK),
    .ENB(
    (i == 0) ?
  (
    (MODO == 2'b00 || MODO == 2'b10 || MODO == 2'b11) ?
    (
      (Q_reg[0] == 4'b0000 && Q_reg[1] == 4'b0000 &&
      Q_reg[2] == 4'b0000 && Q_reg[3] == 4'b0000) ?
      1'b1 : ENB
    ) :
    (
      (Q_reg[0] == 4'b0000 && Q_reg[1] == 4'b0000 &&
      Q_reg[2] == 4'b0000 && Q_reg[3] == 4'b0000) ?
      1'b0 : ENB
    )
  )
  :
  (
    (MODO == 2'b01 && Q_reg[i] == 4'b0000) ?
    1'b0 : RCO_reg[i-1]
  )
),
    .MODO((i == 0) ? MODO : ((MODO == 2'b10) ? 2'b00 : MODO)),
    .D(D_reg[i]),
    .Q(Q_reg[i]),  // Agregada la coma aquí
    .RCO(RCO_reg[i]),
    .Paridad(Paridad_reg[i])
);

           
            // Copia las salidas de los contadores individuales al vector de salida total
            assign Q[i*4 +: 4] = Q_reg[i];
        end
        
    endgenerate

    always @(posedge CLK) begin
        RCO <= RCO_reg[N/4-1]; // El último RCO será el RCO global, nota no se si hay que arreglar el rco
    end

    always @* begin
           // Paridad podría necesitar cálculo adicional, dependiendo de la especificación
        Paridad <= Paridad_reg[0] ^ Paridad_reg[1] ^ Paridad_reg[2] ^ Paridad_reg[3];
    end
endmodule

B90034/Testbench_Tarea1.v
`include "ProbadorTarea1.v"
`include "ContadorTarea1.v"
`include "Contador4X4.v"
                                        
module Contador_TB;

	wire CLK;
	wire ENB;
	wire [15 :0] D;
	wire [1:0] MODO;
	wire [15 :0] Q;
	wire RCO;
	wire Paridad;
	
    initial begin
        $dumpfile("resultados_Tarea1.vcd");
        $dumpvars(0, F1);
        $monitor("D=%b,Q=%b,RCO=%b,Paridad=%b", D, Q, RCO, Paridad);
    end

    //counter U0 (
        //.CLK(CLK), 
        //.ENB(ENB), 
        //.D(D),  
        //.MODO(MODO),
        //.Q(Q),
        //.RCO(RCO), 
        //.Paridad(Paridad)
    //);
    
    Contador F1(
    	.CLK(CLK), 
        .ENB(ENB), 
        .D(D),
        .MODO(MODO),
        .Q(Q),
        .RCO(RCO), 
        .Paridad(Paridad)
    );

    Probador P0 (
        .CLK(CLK), 
        .ENB(ENB), 
        .D(D),
        .MODO(MODO),
        .Q(Q),
        .RCO(RCO), 
        .Paridad(Paridad)
    );
    
endmodule

B90034/resultados_Tarea1.vcd
$date
	Sun Sep 10 19:57:01 2023
$end
$version
	Icarus Verilog
$end
$timescale
	1s
$end
$scope module Contador_TB $end
$scope module F1 $end
$var wire 16 ! Q [15:0] $end
$var wire 2 " MODO [1:0] $end
$var wire 1 # ENB $end
$var wire 16 $ D [15:0] $end
$var wire 1 % CLK $end
$var reg 1 & Paridad $end
$var reg 1 ' RCO $end
$scope begin inst_counter[0] $end
$scope module uut $end
$var wire 4 ( D [3:0] $end
$var wire 1 ) ENB $end
$var wire 2 * MODO [1:0] $end
$var wire 1 % CLK $end
$var reg 1 + Paridad $end
$var reg 4 , Q [3:0] $end
$var reg 1 - RCO $end
$upscope $end
$upscope $end
$scope begin inst_counter[1] $end
$scope module uut $end
$var wire 4 . D [3:0] $end
$var wire 1 / ENB $end
$var wire 2 0 MODO [1:0] $end
$var wire 1 % CLK $end
$var reg 1 1 Paridad $end
$var reg 4 2 Q [3:0] $end
$var reg 1 3 RCO $end
$upscope $end
$upscope $end
$scope begin inst_counter[2] $end
$scope module uut $end
$var wire 4 4 D [3:0] $end
$var wire 1 5 ENB $end
$var wire 2 6 MODO [1:0] $end
$var wire 1 % CLK $end
$var reg 1 7 Paridad $end
$var reg 4 8 Q [3:0] $end
$var reg 1 9 RCO $end
$upscope $end
$upscope $end
$scope begin inst_counter[3] $end
$scope module uut $end
$var wire 4 : D [3:0] $end
$var wire 1 ; ENB $end
$var wire 2 < MODO [1:0] $end
$var wire 1 % CLK $end
$var reg 1 = Paridad $end
$var reg 4 > Q [3:0] $end
$var reg 1 ? RCO $end
$upscope $end
$upscope $end
$upscope $end
$upscope $end
$enddefinitions $end
#0
$dumpvars
x?
bx >
x=
b11 <
x;
b0 :
x9
bx 8
x7
b11 6
x5
b0 4
x3
bx 2
x1
b11 0
x/
b0 .
x-
bx ,
x+
b11 *
1)
b0 (
x'
x&
0%
b0 $
1#
b11 "
bx !
$end
#5
0/
0-
bx0000 !
b0 ,
1%
#10
b0 <
b0 6
b0 0
0%
b0 "
b0 *
#15
bx0001 !
b1 ,
1%
#20
0%
#25
bx0010 !
b10 ,
1%
#30
0%
#35
bx0011 !
b11 ,
1%
#40
0%
#45
bx0100 !
b100 ,
1%
#50
0%
#55
bx0101 !
b101 ,
1%
#60
0%
#65
bx0110 !
b110 ,
1%
#70
0%
#75
bx0111 !
b111 ,
1%
#80
0%
#85
bx1000 !
b1000 ,
1%
#90
0%
#95
bx1001 !
b1001 ,
1%
#100
0%
#105
bx1010 !
b1010 ,
1%
#110
0%
#115
bx1011 !
b1011 ,
1%
#120
0%
#125
bx1100 !
b1100 ,
1%
#130
0%
#135
bx1101 !
b1101 ,
1%
#140
0%
#145
bx1110 !
b1110 ,
1%
#150
0%
#155
1/
1-
bx1111 !
b1111 ,
1%
#160
0%
#165
0/
0-
bx0000 !
b0 ,
1%
#170
0%
#175
bx0001 !
b1 ,
1%
#180
0%
#185
bx0010 !
b10 ,
1%
#190
0%
#195
bx0011 !
b11 ,
1%
#200
0%
#205
bx0100 !
b100 ,
1%
#210
0%
#215
bx0101 !
b101 ,
1%
#220
0)
0%
0#
#225
1%
#230
0%
#235
1%
#240
0%
#245
1%
#250
0%
#255
1%
#260
1)
b11 <
b11 6
b11 0
b1111 (
0%
b11 "
b11 *
b1111 $
1#
#265
1/
1-
bx1111 !
b1111 ,
1%
#270
x/
b1 <
b1 6
b1 0
0%
b1 "
b1 *
#275
0/
0-
bx1110 !
b1110 ,
1%
#280
0%
#285
bx1101 !
b1101 ,
1%
#290
0%
#295
bx1100 !
b1100 ,
1%
#300
0%
#305
bx1011 !
b1011 ,
1%
#310
0%
#315
bx1010 !
b1010 ,
1%
#320
0%
#325
bx1001 !
b1001 ,
1%
#330
0%
#335
bx1000 !
b1000 ,
1%
#340
0%
#345
bx0111 !
b111 ,
1%
#350
0%
#355
bx0110 !
b110 ,
1%
#360
0%
#365
bx0101 !
b101 ,
1%
#370
0%
#375
bx0100 !
b100 ,
1%
#380
0%
#385
bx0011 !
b11 ,
1%
#390
0%
#395
bx0010 !
b10 ,
1%
#400
0%
#405
bx0001 !
b1 ,
1%
#410
0%
#415
x)
bx0000 !
b0 ,
1%
#420
0%
#425
1%
#430
0%
#435
1%
#440
0%
#445
1%
#450
0%
#455
1%
#460
0%
#465
1%
#470
0)
0%
0#
#475
1%
#480
0%
#485
1%
#490
0%
#495
1%
#500
0%
#505
1%
#510
1)
b11 <
b11 6
b11 0
b0 (
0%
b11 "
b11 *
b0 $
1#
#515
1%
#520
b0 <
b0 6
b0 0
0%
b10 "
b10 *
#525
bx0011 !
b11 ,
1%
#530
0%
#535
bx0110 !
b110 ,
1%
#540
0%
#545
bx1001 !
b1001 ,
1%
#550
0%
#555
bx1100 !
b1100 ,
1%
#560
0%
#565
1/
1-
bx1111 !
b1111 ,
1%
#570
0%
#575
0/
0-
bx0010 !
b10 ,
1%
#580
0%
#585
bx0101 !
b101 ,
1%
#590
0%
#595
bx1000 !
b1000 ,
1%
#600
0%
#605
bx1011 !
b1011 ,
1%
#610
0%
#615
bx1110 !
b1110 ,
1%
#620
0%
#625
bx0001 !
b1 ,
1%
#630
0%
#635
bx0100 !
b100 ,
1%
#640
0%
#645
bx0111 !
b111 ,
1%
#650
0%
#655
bx1010 !
b1010 ,
1%
#660
0%
#665
bx1101 !
b1101 ,
1%
#670
0%
#675
bx0000 !
b0 ,
1%
#680
0%
#685
bx0011 !
b11 ,
1%
#690
0%
#695
bx0110 !
b110 ,
1%
#700
0%
#705
bx1001 !
b1001 ,
1%
#710
0%
#715
bx1100 !
b1100 ,
1%
#720
0)
0%
0#
#725
1%
#730
0%
#735
1%
#740
0%
#745
1%
#750
0%
#755
1%
#760
1)
bx (
0%
b0xxxx $
1#
#765
1/
1-
bx1111 !
b1111 ,
1%
#770
b11 <
b11 6
b11 0
0%
b11 "
b11 *
#775
05
0/
03
0-
b0 2
bx0000xxxx !
bx ,
1%
#780
0%
#785
1%
#790
b1001 (
0%
b1001 $
#795
bx00001001 !
b1001 ,
1%
#800
0%
#805
1%
#810
0%
#815
1%
#820
0%
#825
1%
#830
b0 <
b0 6
b0 0
0%
b0 "
b0 *
#835
bx00001010 !
b1010 ,
1%
#840
0%
#845
bx00001011 !
b1011 ,
1%
#850
0%
#855
bx00001100 !
b1100 ,
1%
#860
0%
#865
bx00001101 !
b1101 ,
1%
#870
0%
#875
bx00001110 !
b1110 ,
1%
#880
0%
#885
1/
1-
bx00001111 !
b1111 ,
1%
#890
0%
#895
0/
0-
b1 2
bx00010000 !
b0 ,
1%
#900
0%
#905
bx00010001 !
b1 ,
1%
#910
0%
#915
bx00010010 !
b10 ,
1%
#920
0%
#925
bx00010011 !
b11 ,
1%
#930
0%
#935
bx00010100 !
b100 ,
1%
#940
0%
#945
bx00010101 !
b101 ,
1%
#950
0%
#955
bx00010110 !
b110 ,
1%
#960
0%
#965
bx00010111 !
b111 ,
1%
#970
0%
#975
bx00011000 !
b1000 ,
1%
#980
0%
#985
bx00011001 !
b1001 ,
1%
#990
0%
#995
bx00011010 !
b1010 ,
1%
#1000
0%
#1005
bx00011011 !
b1011 ,
1%
#1010
0%
#1015
bx00011100 !
b1100 ,
1%
#1020
0%
#1025
bx00011101 !
b1101 ,
1%
#1030
0%
#1035
bx00011110 !
b1110 ,
1%
#1040
0%
#1045
1/
1-
bx00011111 !
b1111 ,
1%
#1050
0%
#1055
0/
0-
b10 2
bx00100000 !
b0 ,
1%
#1060
0%
#1065
bx00100001 !
b1 ,
1%
#1070
0%
#1075
bx00100010 !
b10 ,
1%
#1080
0)
0%
0#
#1085
1%
#1090
0%
#1095
1%
#1100
0%
#1105
1%
#1110
0%
#1115
1%
#1120
1)
b11 <
b11 6
b11 0
b0 (
0%
b11 "
b11 *
b0 $
1#
#1125
bx00100000 !
b0 ,
1%
#1130
b0 <
b0 6
b0 0
0%
b0 "
b0 *
#1135
bx00100001 !
b1 ,
1%
#1140
0%
#1145
bx00100010 !
b10 ,
1%
#1150
0%
#1155
bx00100011 !
b11 ,
1%
#1160
0%
#1165
bx00100100 !
b100 ,
1%
#1170
0%
#1175
bx00100101 !
b101 ,
1%
#1180
0%
#1185
bx00100110 !
b110 ,
1%
#1190
0%
#1195
bx00100111 !
b111 ,
1%
#1200
0%
#1205
bx00101000 !
b1000 ,
1%
#1210
0%
#1215
bx00101001 !
b1001 ,
1%
#1220
0%
#1225
bx00101010 !
b1010 ,
1%
#1230
0%
#1235
bx00101011 !
b1011 ,
1%
#1240
0%
#1245
bx00101100 !
b1100 ,
1%
#1250
b1 <
b1 6
b1 0
0%
b1 "
b1 *
#1255
bx00101011 !
b1011 ,
1%
#1260
0%
#1265
bx00101010 !
b1010 ,
1%
#1270
0%
#1275
bx00101001 !
b1001 ,
1%
#1280
0%
#1285
bx00101000 !
b1000 ,
1%
#1290
0%
#1295
bx00100111 !
b111 ,
1%
#1300
0%
#1305
bx00100110 !
b110 ,
1%
#1310
0%
#1315
bx00100101 !
b101 ,
1%
#1320
0%
#1325
bx00100100 !
b100 ,
1%
#1330
0%
#1335
bx00100011 !
b11 ,
1%
#1340
0%
#1345
bx00100010 !
b10 ,
1%
#1350
0%
#1355
bx00100001 !
b1 ,
1%
#1360
0%
#1365
bx00100000 !
b0 ,
1%
#1370
b0 <
b0 6
b0 0
0%
b10 "
b10 *
#1375
bx00100011 !
b11 ,
1%
#1380
0%
#1385
bx00100110 !
b110 ,
1%
#1390
0%
#1395
bx00101001 !
b1001 ,
1%
#1400
0%
#1405
bx00101100 !
b1100 ,
1%
#1410
0%
#1415
1/
1-
bx00101111 !
b1111 ,
1%
#1420
0%
#1425
0/
0-
b10 ,
bx00110010 !
b11 2
1%
#1430
0%
#1435
bx00110101 !
b101 ,
1%
#1440
0%
#1445
bx00111000 !
b1000 ,
1%
#1450
0%
#1455
bx00111011 !
b1011 ,
1%
#1460
0%
#1465
bx00111110 !
b1110 ,
1%
#1470
0%
#1475
bx00110001 !
b1 ,
1%
#1480
0%
#1485
bx00110100 !
b100 ,
1%
#1490
b11 <
b11 6
b11 0
b1 .
b1110 (
0%
b11 "
b11 *
b11110 $
#1495
bx00111110 !
b1110 ,
1%
